{
  "recentFiles": [
    {
      "basename": "BufferedReader和BufferedWriter的作用",
      "path": "2 - Source Material/AI/BufferedReader和BufferedWriter的作用.md"
    },
    {
      "basename": "继承",
      "path": "6 - Main Notes/继承.md"
    },
    {
      "basename": "Java中访问权限的继承",
      "path": "6 - Main Notes/Java中访问权限的继承.md"
    },
    {
      "basename": "封装(Encapsulation)",
      "path": "6 - Main Notes/封装(Encapsulation).md"
    },
    {
      "basename": "Java 继承中访问权限的规则",
      "path": "2 - Source Material/AI/Java 继承中访问权限的规则.md"
    },
    {
      "basename": "Java中的访问权限(Scope)",
      "path": "6 - Main Notes/Java中的访问权限(Scope).md"
    },
    {
      "basename": "super关键字",
      "path": "6 - Main Notes/super关键字.md"
    },
    {
      "basename": "this关键字",
      "path": "6 - Main Notes/this关键字.md"
    },
    {
      "basename": "什么是构造方法",
      "path": "2 - Source Material/AI/什么是构造方法.md"
    },
    {
      "basename": "构造器(Constructor)",
      "path": "构造方法/构造器(Constructor).md"
    },
    {
      "basename": "this关键字和super关键字的用法",
      "path": "2 - Source Material/AI/this关键字和super关键字的用法.md"
    },
    {
      "basename": "this关键字和super关键字对比",
      "path": "2 - Source Material/AI/this关键字和super关键字对比.md"
    },
    {
      "basename": "OOP",
      "path": "3 - Tags/OOP.md"
    },
    {
      "basename": "Lambda表达式简单理解",
      "path": "6 - Main Notes/Lambda表达式简单理解.md"
    },
    {
      "basename": "函数式编程(Functional Programming)",
      "path": "6 - Main Notes/函数式编程(Functional Programming).md"
    },
    {
      "basename": "Java",
      "path": "3 - Tags/Java.md"
    },
    {
      "basename": "为什么需要封装(Encapsulation)",
      "path": "6 - Main Notes/为什么需要封装(Encapsulation).md"
    },
    {
      "basename": "在java中多态是如何实现的",
      "path": "2 - Source Material/AI/在java中多态是如何实现的.md"
    },
    {
      "basename": "What is Polymorphism",
      "path": "6 - Main Notes/What is Polymorphism.md"
    },
    {
      "basename": "向上转型(Upcasting)",
      "path": "6 - Main Notes/向上转型(Upcasting).md"
    },
    {
      "basename": "为什么不使用Object作为引用类型",
      "path": "2 - Source Material/AI/为什么不使用Object作为引用类型.md"
    },
    {
      "basename": "多态(Polymorphism)",
      "path": "6 - Main Notes/多态(Polymorphism).md"
    },
    {
      "basename": "Java中如何实现多态",
      "path": "6 - Main Notes/Java中如何实现多态.md"
    },
    {
      "basename": "方法重载(Method Overloading)",
      "path": "6 - Main Notes/方法重载(Method Overloading).md"
    },
    {
      "basename": "方法重写(Method Overriding)",
      "path": "6 - Main Notes/方法重写(Method Overriding).md"
    },
    {
      "basename": "Template-Main Note",
      "path": "5 - Templates/Template-Main Note.md"
    },
    {
      "basename": "什么是多态, 为什么我们需要多态",
      "path": "2 - Source Material/AI/什么是多态, 为什么我们需要多态.md"
    },
    {
      "basename": "超前学习的结果是超前放弃",
      "path": "6 - Main Notes/超前学习的结果是超前放弃.md"
    },
    {
      "basename": "对学习的恐惧",
      "path": "1 - Rough Notes/对学习的恐惧.md"
    },
    {
      "basename": "baby",
      "path": "6 - Main Notes/baby.md"
    },
    {
      "basename": "接口和抽象类",
      "path": "6 - Main Notes/接口和抽象类.md"
    },
    {
      "basename": "talk with ai",
      "path": "3 - Tags/talk with ai.md"
    },
    {
      "basename": "烦恼是被允许的",
      "path": "6 - Main Notes/烦恼是被允许的.md"
    },
    {
      "basename": "为什么推荐使用语音来记录信息",
      "path": "6 - Main Notes/为什么推荐使用语音来记录信息.md"
    },
    {
      "basename": "什么是好的Presentation",
      "path": "6 - Main Notes/什么是好的Presentation.md"
    },
    {
      "basename": "有限与无限",
      "path": "6 - Main Notes/有限与无限.md"
    },
    {
      "basename": "计算机七大思想",
      "path": "6 - Main Notes/计算机七大思想.md"
    },
    {
      "basename": "学生终究会超越老师",
      "path": "6 - Main Notes/学生终究会超越老师.md"
    },
    {
      "basename": "时间刻上你的皱纹, 阅读留下书的折痕",
      "path": "6 - Main Notes/时间刻上你的皱纹, 阅读留下书的折痕.md"
    },
    {
      "basename": "对时间的利用",
      "path": "6 - Main Notes/对时间的利用.md"
    },
    {
      "basename": "为什么要去做不起眼的事",
      "path": "6 - Main Notes/为什么要去做不起眼的事.md"
    },
    {
      "basename": "有的人-臧克家",
      "path": "2 - Source Material/文章/有的人-臧克家.md"
    },
    {
      "basename": "无法控制的学习",
      "path": "6 - Main Notes/无法控制的学习.md"
    },
    {
      "basename": "关于天赋的确认",
      "path": "6 - Main Notes/关于天赋的确认.md"
    },
    {
      "basename": "有限的学校 无限的学习",
      "path": "6 - Main Notes/有限的学校 无限的学习.md"
    },
    {
      "basename": "白鸽子黑鸽子",
      "path": "6 - Main Notes/白鸽子黑鸽子.md"
    },
    {
      "basename": "景色印象",
      "path": "3 - Tags/景色印象.md"
    },
    {
      "basename": "绝不要携带两个时钟出海, 带一个或者三个",
      "path": "6 - Main Notes/绝不要携带两个时钟出海, 带一个或者三个.md"
    },
    {
      "basename": "团队合作中最有价值的是工作产品",
      "path": "6 - Main Notes/团队合作中最有价值的是工作产品.md"
    },
    {
      "basename": "人与人无法相互理解",
      "path": "6 - Main Notes/人与人无法相互理解.md"
    }
  ],
  "omittedPaths": [],
  "omittedTags": [],
  "omitBookmarks": false
}